{
    "id": 125440465,
    "name": "Crystal Breaker",
    "author": "Seth",
    "creators": ["Seth"],
    "verifier": "Hyrounz",
    "verification": "https://youtu.be/CxVvBuNkKPk?si=fVDHvotIkRrgDaZj",
    "percentToQualify": "100",
    "password": "Free To Copy",
    "records": [
        {
            "user": "feisaran",
            "link": "https://www.youtube.com/watch?v=Hk9owML-yYQ",
            "percent": 100
        },
        {
            "user": "Loxo",
            "link": "https://youtu.be/ReG9XuOIPAw",
            "percent": 100
        }
    ]
}
