{
    "id": 125788975,
    "name": "Z aim bocou manzer",
    "author": "MedineOnGD",
    "creators": ["MedineOnGD"],
    "verifier": "Ghouno",
    "verification": "https://youtu.be/wxXWHCJ756Y",
    "percentToQualify": "100",
    "password": "Free To Copy",
    "records": [
        {
            "user": "Loxo",
            "link": "https://youtu.be/ps6lw7aTqGg",
            "percent": 100
        },
        {
            "user": "MedineOnGD",
            "link": "https://youtube.com/shorts/qpgJCG9gJhE?feature=shared",
            "percent": 100
        },
        {
            "user": "ioi890",
            "link": "https://youtu.be/tE1KPGDgJVk",
            "percent": 100
        },
        {
            "user": "mstr",
            "link": "https://www.youtube.com/watch?v=hY8W0l9PPtA",
            "percent": 100
        },
        {
            "user": "kitemy",
            "link": "https://youtu.be/ZfGQrJw-aM4",
            "percent": 100
        },
        {
    "user": "Zephyrlawg",
    "link": "https://youtu.be/FeLvI5wu8t0",
    "percent": 100
},
        {
    "user": "Senko",
    "link": "https://youtu.be/YsfHZAFeVLA",
    "percent": 100
},
        {
    "user": "Darkad",
    "link": "https://www.youtube.com/watch?v=tOlHVxlsQdY",
    "percent": 100
},
        {
    "user": "zlayse",
    "link": "https://youtu.be/yTfurgFGkm8",
    "percent": 100
},
        {
    "user": "YoumanJY",
    "link": "https://youtu.be/rWKlQnEmNc8",
    "percent": 100
},
        {
    "user": "FloLink212",
    "link": "https://youtu.be/20KpS5CP6K0?si=4QrGLWOcE2LmWGIg",
    "percent": 100
},
        {
    "user": "RK Raze",
    "link": "https://youtu.be/bejNYgItqQ8",
    "percent": 100
},
        {
    "user": "noctashi",
    "link": "https://youtu.be/fJzrClFnngI?si=UBwR-NyBsH8gBF5w",
    "percent": 100
},
        {
    "user": "Melody",
    "link": "https://youtu.be/SYZYB1kXHhU",
    "percent": 100
},
        {
    "user": "zAthena",
    "link": "https://youtu.be/PFfYUCyZofo?si=vVE5sjtfkJ4tDDyQ",
    "percent": 100
},
        {
    "user": "Letanguu",
    "link": "https://youtu.be/CrJ2iLsm7EA?si=NvqME4LcZOLCRGsl",
    "percent": 100
},
        {
    "user": "Chatonmanitou21",
    "link": "https://youtu.be/rmrm9_uMcJ8?si=fPcbsIEdUqr1hDfF",
    "percent": 100
},
        {
    "user": "EviV2",
    "link": "https://youtu.be/-tTsdhrZQH0",
    "percent": 100
},
        {
    "user": "Bluud",
    "link": "https://youtu.be/A4X5ugpyZP8",
    "percent": 100
}
    ]
}
